[
    {
        "date": "2024-10-03",
        "price": 48
    },
    {
        "date": "2024-10-04",
        "price": 50
    },
    {
        "date": "2024-10-05",
        "price": 56
    },
    {
        "date": "2024-10-06",
        "price": 54
    },
    {
        "date": "2024-10-07",
        "price": 50
    },
    {
        "date": "2024-10-08",
        "price": 50
    },
    {
        "date": "2024-10-09",
        "price": 50
    },
    {
        "date": "2024-10-10",
        "price": 50
    },
    {
        "date": "2024-10-11",
        "price": 52
    },
    {
        "date": "2024-10-12",
        "price": 56
    },
    {
        "date": "2024-10-13",
        "price": 54
    },
    {
        "date": "2024-10-14",
        "price": 48
    },
    {
        "date": "2024-10-15",
        "price": 48
    },
    {
        "date": "2024-10-16",
        "price": 48
    },
    {
        "date": "2024-10-17",
        "price": 48
    },
    {
        "date": "2024-10-18",
        "price": 52
    },
    {
        "date": "2024-10-19",
        "price": 56
    },
    {
        "date": "2024-10-20",
        "price": 54
    },
    {
        "date": "2024-10-21",
        "price": 52
    },
    {
        "date": "2024-10-22",
        "price": 52
    },
    {
        "date": "2024-10-23",
        "price": 52
    },
    {
        "date": "2024-10-24",
        "price": 52
    },
    {
        "date": "2024-10-25",
        "price": 52
    },
    {
        "date": "2024-10-26",
        "price": 56
    },
    {
        "date": "2024-10-27",
        "price": 54
    },
    {
        "date": "2024-10-28",
        "price": 52
    },
    {
        "date": "2024-10-29",
        "price": 52
    },
    {
        "date": "2024-10-30",
        "price": 52
    },
    {
        "date": "2024-10-31",
        "price": 60
    },
    {
        "date": "2024-11-01",
        "price": 60
    },
    {
        "date": "2024-11-02",
        "price": 60
    },
    {
        "date": "2024-11-03",
        "price": 56
    },
    {
        "date": "2024-11-04",
        "price": 48
    },
    {
        "date": "2024-11-05",
        "price": 48
    },
    {
        "date": "2024-11-06",
        "price": 48
    },
    {
        "date": "2024-11-07",
        "price": 48
    },
    {
        "date": "2024-11-08",
        "price": 48
    },
    {
        "date": "2024-11-09",
        "price": 56
    },
    {
        "date": "2024-11-10",
        "price": 54
    },
    {
        "date": "2024-11-11",
        "price": 40
    },
    {
        "date": "2024-11-12",
        "price": 40
    },
    {
        "date": "2024-11-13",
        "price": 40
    },
    {
        "date": "2024-11-14",
        "price": 40
    },
    {
        "date": "2024-11-15",
        "price": 40
    },
    {
        "date": "2024-11-16",
        "price": 52
    },
    {
        "date": "2024-11-17",
        "price": 52
    },
    {
        "date": "2024-11-18",
        "price": 40
    },
    {
        "date": "2024-11-19",
        "price": 40
    },
    {
        "date": "2024-11-20",
        "price": 40
    },
    {
        "date": "2024-11-21",
        "price": 40
    },
    {
        "date": "2024-11-22",
        "price": 40
    },
    {
        "date": "2024-11-23",
        "price": 52
    },
    {
        "date": "2024-11-24",
        "price": 52
    },
    {
        "date": "2024-11-25",
        "price": 40
    },
    {
        "date": "2024-11-26",
        "price": 40
    },
    {
        "date": "2024-11-27",
        "price": 40
    },
    {
        "date": "2024-11-28",
        "price": 40
    },
    {
        "date": "2024-11-29",
        "price": 40
    },
    {
        "date": "2024-11-30",
        "price": 52
    },
    {
        "date": "2024-12-01",
        "price": 52
    },
    {
        "date": "2024-12-02",
        "price": 40
    },
    {
        "date": "2024-12-03",
        "price": 40
    },
    {
        "date": "2024-12-04",
        "price": 40
    },
    {
        "date": "2024-12-05",
        "price": 40
    },
    {
        "date": "2024-12-06",
        "price": 54
    },
    {
        "date": "2024-12-07",
        "price": 54
    },
    {
        "date": "2024-12-08",
        "price": 52
    },
    {
        "date": "2024-12-09",
        "price": 40
    },
    {
        "date": "2024-12-10",
        "price": 40
    },
    {
        "date": "2024-12-11",
        "price": 40
    },
    {
        "date": "2024-12-12",
        "price": 40
    },
    {
        "date": "2024-12-13",
        "price": 40
    },
    {
        "date": "2024-12-14",
        "price": 52
    },
    {
        "date": "2024-12-15",
        "price": 52
    },
    {
        "date": "2024-12-16",
        "price": 40
    },
    {
        "date": "2024-12-17",
        "price": 40
    },
    {
        "date": "2024-12-18",
        "price": 40
    },
    {
        "date": "2024-12-19",
        "price": 40
    },
    {
        "date": "2024-12-20",
        "price": 40
    },
    {
        "date": "2024-12-21",
        "price": 52
    },
    {
        "date": "2024-12-22",
        "price": 52
    },
    {
        "date": "2024-12-23",
        "price": 52
    },
    {
        "date": "2024-12-24",
        "price": 52
    },
    {
        "date": "2024-12-25",
        "price": 52
    },
    {
        "date": "2024-12-26",
        "price": 54
    },
    {
        "date": "2024-12-27",
        "price": 54
    },
    {
        "date": "2024-12-28",
        "price": 54
    },
    {
        "date": "2024-12-29",
        "price": 54
    },
    {
        "date": "2024-12-30",
        "price": 54
    },
    {
        "date": "2024-12-31",
        "price": 52
    },
    {
        "date": "2025-01-01",
        "price": 54
    },
    {
        "date": "2025-01-02",
        "price": 54
    },
    {
        "date": "2025-01-03",
        "price": 54
    },
    {
        "date": "2025-01-04",
        "price": 54
    },
    {
        "date": "2025-01-05",
        "price": 54
    },
    {
        "date": "2025-01-06",
        "price": 52
    }
]